Workbook

Sheet Assumptions
C3: DataSense Commercial Planning Model
C5: Editable planning model — assumptions require validation
C6: USD unless stated otherwise
C8: Scenario Selection
C9: Selected scenario | D9: Base
C12: Scenario Drivers
C13: Driver | D13: Downside | E13: Base | F13: Upside
C14: Annual Professional seat growth | D14: 0.4 | E14: 0.8 | F14: 1.3
C15: Annual Professional churn | D15: 0.3 | E15: 0.2 | F15: 0.14
C16: Annual Team-logo growth | D16: 0.2 | E16: 0.6 | F16: 1
C17: Annual Team-logo churn | D17: 0.18 | E17: 0.12 | F17: 0.08
C18: Enterprise wins — Year 1 | D18: 0 | E18: 1 | F18: 2
C19: Enterprise win growth | D19: 0.1 | E19: 0.5 | F19: 0.75
C20: Subscription gross margin | D20: 0.7 | E20: 0.78 | F20: 0.83
C21: R&D annual expense growth | D21: 0.15 | E21: 0.2 | F21: 0.28
C22: Sales & success annual expense growth | D22: 0.1 | E22: 0.25 | F22: 0.4
C23: G&A annual expense growth | D23: 0.08 | E23: 0.15 | F23: 0.2
C26: Commercial Inputs
C27: Starting Professional seats — Year 1 | D27: 50
C28: Professional monthly price | D28: 39
C29: Starting Team logos — Year 1 | D29: 2
C30: Team annual contract value | D30: 5000
C31: Starting Enterprise logos | D31: 0
C32: Enterprise annual contract value | D32: 30000
C33: Enterprise onboarding fee | D33: 7500
C34: R&D expense — Year 1 | D34: 200000
C35: Sales & success expense — Year 1 | D35: 50000
C36: G&A expense — Year 1 | D36: 30000
C39: Scenario Resolution
C40: Selected Professional growth | D40: =INDEX($D$14:$F$14,1,MATCH($D$9,$D$13:$F$13,0))
C41: Selected Professional churn | D41: =INDEX($D$15:$F$15,1,MATCH($D$9,$D$13:$F$13,0))
C42: Selected Team-logo growth | D42: =INDEX($D$16:$F$16,1,MATCH($D$9,$D$13:$F$13,0))
C43: Selected Team-logo churn | D43: =INDEX($D$17:$F$17,1,MATCH($D$9,$D$13:$F$13,0))
C44: Selected Enterprise wins — Year 1 | D44: =INDEX($D$18:$F$18,1,MATCH($D$9,$D$13:$F$13,0))
C45: Selected Enterprise win growth | D45: =INDEX($D$19:$F$19,1,MATCH($D$9,$D$13:$F$13,0))
C46: Selected Gross margin | D46: =INDEX($D$20:$F$20,1,MATCH($D$9,$D$13:$F$13,0))
C47: Selected R&D growth | D47: =INDEX($D$21:$F$21,1,MATCH($D$9,$D$13:$F$13,0))
C48: Selected Sales & success growth | D48: =INDEX($D$22:$F$22,1,MATCH($D$9,$D$13:$F$13,0))
C49: Selected G&A growth | D49: =INDEX($D$23:$F$23,1,MATCH($D$9,$D$13:$F$13,0))

Sheet Revenue
C3: Revenue Build
C5: Driver-based annual revenue and ARR planning
C6: USD unless stated otherwise
C8: Metric | D8: 2026E | E8: 2027E | F8: 2028E | G8: 2029E | H8: 2030E
C10: Professional Subscription
C11: Active Professional seats | D11: =Assumptions!$D$27 | E11: =D11*(1+Assumptions!$D$40)*(1-Assumptions!$D$41) | F11: =E11*(1+Assumptions!$D$40)*(1-Assumptions!$D$41) | G11: =F11*(1+Assumptions!$D$40)*(1-Assumptions!$D$41) | H11: =G11*(1+Assumptions!$D$40)*(1-Assumptions!$D$41)
C12: Monthly price per seat | D12: =Assumptions!$D$28 | E12: =Assumptions!$D$28 | F12: =Assumptions!$D$28 | G12: =Assumptions!$D$28 | H12: =Assumptions!$D$28
C13: Professional ARR | D13: =D11*D12*12 | E13: =E11*E12*12 | F13: =F11*F12*12 | G13: =G11*G12*12 | H13: =H11*H12*12
C15: Team Contracts
C16: Active Team logos | D16: =Assumptions!$D$29 | E16: =D16*(1+Assumptions!$D$42)*(1-Assumptions!$D$43) | F16: =E16*(1+Assumptions!$D$42)*(1-Assumptions!$D$43) | G16: =F16*(1+Assumptions!$D$42)*(1-Assumptions!$D$43) | H16: =G16*(1+Assumptions!$D$42)*(1-Assumptions!$D$43)
C17: Team annual contract value | D17: =Assumptions!$D$30 | E17: =Assumptions!$D$30 | F17: =Assumptions!$D$30 | G17: =Assumptions!$D$30 | H17: =Assumptions!$D$30
C18: Team ARR | D18: =D16*D17 | E18: =E16*E17 | F18: =F16*F17 | G18: =G16*G17 | H18: =H16*H17
C20: Enterprise Contracts
C21: Enterprise wins | D21: =Assumptions!$D$44 | E21: =D21*(1+Assumptions!$D$45) | F21: =E21*(1+Assumptions!$D$45) | G21: =F21*(1+Assumptions!$D$45) | H21: =G21*(1+Assumptions!$D$45)
C22: Active Enterprise logos | D22: =Assumptions!$D$31+D21 | E22: =D22+E21 | F22: =E22+F21 | G22: =F22+G21 | H22: =G22+H21
C23: Enterprise annual contract value | D23: =Assumptions!$D$32 | E23: =Assumptions!$D$32 | F23: =Assumptions!$D$32 | G23: =Assumptions!$D$32 | H23: =Assumptions!$D$32
C24: Enterprise ARR | D24: =D22*D23 | E24: =E22*E23 | F24: =F22*F23 | G24: =G22*G23 | H24: =H22*H23
C25: Onboarding revenue | D25: =D21*Assumptions!$D$33 | E25: =E21*Assumptions!$D$33 | F25: =F21*Assumptions!$D$33 | G25: =G21*Assumptions!$D$33 | H25: =H21*Assumptions!$D$33
C27: Total subscription ARR | D27: =D13+D18+D24 | E27: =E13+E18+E24 | F27: =F13+F18+F24 | G27: =G13+G18+G24 | H27: =H13+H18+H24
C28: Total revenue | D28: =D27+D25 | E28: =E27+E25 | F28: =F27+F25 | G28: =G27+G25 | H28: =H27+H25

Sheet Operating Model
C3: Operating Model
C5: Revenue, gross profit and planning EBITDA
C6: USD unless stated otherwise
C8: Metric | D8: 2026E | E8: 2027E | F8: 2028E | G8: 2029E | H8: 2030E
C10: Income Statement
C11: Revenue | D11: =Revenue!D28 | E11: =Revenue!E28 | F11: =Revenue!F28 | G11: =Revenue!G28 | H11: =Revenue!H28
C12: Cost of revenue | D12: =-D11*(1-Assumptions!$D$46) | E12: =-E11*(1-Assumptions!$D$46) | F12: =-F11*(1-Assumptions!$D$46) | G12: =-G11*(1-Assumptions!$D$46) | H12: =-H11*(1-Assumptions!$D$46)
C13: Gross profit | D13: =D11+D12 | E13: =E11+E12 | F13: =F11+F12 | G13: =G11+G12 | H13: =H11+H12
C14: Gross margin | D14: =IFERROR(D13/D11,0) | E14: =IFERROR(E13/E11,0) | F14: =IFERROR(F13/F11,0) | G14: =IFERROR(G13/G11,0) | H14: =IFERROR(H13/H11,0)
C16: R&D | D16: =-Assumptions!$D$34 | E16: =D16*(1+Assumptions!$D$47) | F16: =E16*(1+Assumptions!$D$47) | G16: =F16*(1+Assumptions!$D$47) | H16: =G16*(1+Assumptions!$D$47)
C17: Sales & customer success | D17: =-Assumptions!$D$35 | E17: =D17*(1+Assumptions!$D$48) | F17: =E17*(1+Assumptions!$D$48) | G17: =F17*(1+Assumptions!$D$48) | H17: =G17*(1+Assumptions!$D$48)
C18: G&A | D18: =-Assumptions!$D$36 | E18: =D18*(1+Assumptions!$D$49) | F18: =E18*(1+Assumptions!$D$49) | G18: =F18*(1+Assumptions!$D$49) | H18: =G18*(1+Assumptions!$D$49)
C19: Operating expenses | D19: =D16+D17+D18 | E19: =E16+E17+E18 | F19: =F16+F17+F18 | G19: =G16+G17+G18 | H19: =H16+H17+H18
C21: Planning EBITDA | D21: =D13+D19 | E21: =E13+E19 | F21: =F13+F19 | G21: =G13+G19 | H21: =H13+H19
C22: EBITDA margin | D22: =IFERROR(D21/D11,0) | E22: =IFERROR(E21/E11,0) | F22: =IFERROR(F21/F11,0) | G22: =IFERROR(G21/G11,0) | H22: =IFERROR(H21/H11,0)
C24: Cash burn before financing/tax | D24: =-D21 | E24: =-E21 | F24: =-F21 | G24: =-G21 | H24: =-H21

Sheet KPIs
C3: Commercial KPIs
C5: Planning outputs — replace with observed cohort data when available
C6: USD unless stated otherwise
C8: Metric | D8: 2026E | E8: 2027E | F8: 2028E | G8: 2029E | H8: 2030E
C10: Growth and Efficiency
C11: Professional seats | D11: =Revenue!D11 | E11: =Revenue!E11 | F11: =Revenue!F11 | G11: =Revenue!G11 | H11: =Revenue!H11
C12: Team logos | D12: =Revenue!D16 | E12: =Revenue!E16 | F12: =Revenue!F16 | G12: =Revenue!G16 | H12: =Revenue!H16
C13: Enterprise logos | D13: =Revenue!D22 | E13: =Revenue!E22 | F13: =Revenue!F22 | G13: =Revenue!G22 | H13: =Revenue!H22
C14: Total logos | D14: =D11+D12+D13 | E14: =E11+E12+E13 | F14: =F11+F12+F13 | G14: =G11+G12+G13 | H14: =H11+H12+H13
C16: Subscription ARR | D16: =Revenue!D27 | E16: =Revenue!E27 | F16: =Revenue!F27 | G16: =Revenue!G27 | H16: =Revenue!H27
C17: Total revenue | D17: =Revenue!D28 | E17: =Revenue!E28 | F17: =Revenue!F28 | G17: =Revenue!G28 | H17: =Revenue!H28
C18: Gross profit | D18: ='Operating Model'!D13 | E18: ='Operating Model'!E13 | F18: ='Operating Model'!F13 | G18: ='Operating Model'!G13 | H18: ='Operating Model'!H13
C19: Planning EBITDA | D19: ='Operating Model'!D21 | E19: ='Operating Model'!E21 | F19: ='Operating Model'!F21 | G19: ='Operating Model'!G21 | H19: ='Operating Model'!H21
C21: Revenue growth | D21: =0 | E21: =IFERROR(E17/D17-1,0) | F21: =IFERROR(F17/E17-1,0) | G21: =IFERROR(G17/F17-1,0) | H21: =IFERROR(H17/G17-1,0)
C22: Gross margin | D22: ='Operating Model'!D14 | E22: ='Operating Model'!E14 | F22: ='Operating Model'!F14 | G22: ='Operating Model'!G14 | H22: ='Operating Model'!H14
C23: EBITDA margin | D23: ='Operating Model'!D22 | E23: ='Operating Model'!E22 | F23: ='Operating Model'!F22 | G23: ='Operating Model'!G22 | H23: ='Operating Model'!H22
C25: ARR per logo | D25: =IFERROR(D16/D14,0) | E25: =IFERROR(E16/E14,0) | F25: =IFERROR(F16/F14,0) | G25: =IFERROR(G16/G14,0) | H25: =IFERROR(H16/H14,0)

Sheet Sources
C3: Sources and Model Limits
C5: Source log for hardcoded planning inputs and contextual references
C6: N/A
C8: Source Log
C9: Item | D9: Source / basis | E9: Date | F9: Use in model | G9: Confidence
C10: Commercial prices and growth | D10: Management planning assumptions; not market benchmarks. | E10: 2026-08-14 | F10: Assumptions tab | G10: Low
C11: Market urgency | D11: Evanta/Gartner C-level Communities — Top 3 Priorities for CDAOs in 2025. | E11: 2025 | F11: Strategic context only | G11: Medium
C12: US firm universe | D12: U.S. Census Bureau — Small Business Story. | E12: 2023 data | F12: Not used as TAM | G12: High
C13: EU enterprise universe | D13: Eurostat — Structural Business Statistics Overview. | E13: 2023 data | F13: Not used as TAM | G13: High
C14: UK firm universe | D14: ONS — UK business: activity, size and location. | E14: 2025 | F14: Not used as TAM | G14: High
C17: Model Limits
C18: This is a management planning model, not a valuation or investment forecast.
C19: No historical financial statements were provided; all hardcoded operating inputs are blue and require validation.
C20: The model intentionally contains no TAM/SAM/SOM calculation until the market definition and pricing unit are approved.
C21: All revenue drivers are annual and should be replaced with monthly cohort data before any external financing use.
